{
  "$schema": "https://raw.githubusercontent.com/electron-userland/electron-builder/master/packages/app-builder-lib/scheme.json",
  "appId": "com.trafexia.app",
  "productName": "Trafexia",
  "directories": {
    "output": "release"
  },
  "files": [
    "dist/**/*",
    "dist-electron/**/*"
  ],
  "mac": {
    "target": ["dmg", "zip"],
    "icon": "resources/icons/icon.png",
    "category": "public.app-category.developer-tools",
    "hardenedRuntime": true,
    "gatekeeperAssess": false,
    "entitlements": "build/entitlements.mac.plist",
    "entitlementsInherit": "build/entitlements.mac.plist"
  },
  "afterSign": "scripts/notarize.js",
  "win": {
    "target": ["nsis", "portable"],
    "icon": "resources/icons/icon.png"
  },
  "linux": {
    "target": ["AppImage", "deb"],
    "icon": "resources/icons",
    "category": "Development"
  },
  "nsis": {
    "oneClick": false,
    "allowToChangeInstallationDirectory": true
  },
  "extraResources": [
    {
      "from": "resources",
      "to": "resources"
    }
  ]
}
